Binod/__init__.py
Binod-0.2.0.dist-info/LICENSE
Binod-0.2.0.dist-info/METADATA
Binod-0.2.0.dist-info/WHEEL
Binod-0.2.0.dist-info/top_level.txt
Binod-0.2.0.dist-info/RECORD
